txThings-0.3.0.dist-info/METADATA
txThings-0.3.0.dist-info/RECORD
txThings-0.3.0.dist-info/WHEEL
txThings-0.3.0.dist-info/top_level.txt
txthings/__init__.py
txthings/coap.py
txthings/error.py
txthings/resource.py
txthings/ext/__init__.py
txthings/ext/link_header.py
