Metadata-Version: 2.1
Name: txThings
Version: 0.3.0
Summary: CoAP protocol implementation for Twisted Framework
Home-page: https://github.com/siskin/txThings/
Author: Maciej Wasilak
Author-email: wasilak@gmail.com
License: UNKNOWN
Platform: UNKNOWN
Requires-Dist: twisted (>=14.0.0)
Requires-Dist: six (>=1.10.0)
Requires-Dist: py2-ipaddress (>=3.4.1); python_version < "3.0"
